HuweihuangKubernetesXuexiBiji/README.md
HuweihuangKubernetesXuexiBiji/__init__.py
HuweihuangKubernetesXuexiBiji/__main__.py
HuweihuangKubernetesXuexiBiji/file.epub
HuweihuangKubernetesXuexiBiji/index.html
HuweihuangKubernetesXuexiBiji/css/__init__.py
HuweihuangKubernetesXuexiBiji/css/annotations.css
HuweihuangKubernetesXuexiBiji/css/main.css
HuweihuangKubernetesXuexiBiji/css/normalize.css
HuweihuangKubernetesXuexiBiji/css/popup.css
HuweihuangKubernetesXuexiBiji/font/__init__.py
HuweihuangKubernetesXuexiBiji/font/fontello.eot
HuweihuangKubernetesXuexiBiji/font/fontello.svg
HuweihuangKubernetesXuexiBiji/font/fontello.ttf
HuweihuangKubernetesXuexiBiji/font/fontello.woff
HuweihuangKubernetesXuexiBiji/img/__init__.py
HuweihuangKubernetesXuexiBiji/img/annotator-glyph-sprite.png
HuweihuangKubernetesXuexiBiji/img/annotator-icon-sprite.png
HuweihuangKubernetesXuexiBiji/img/apple-touch-icon.png
HuweihuangKubernetesXuexiBiji/img/cancelfullscreen.png
HuweihuangKubernetesXuexiBiji/img/close.png
HuweihuangKubernetesXuexiBiji/img/fullscreen.png
HuweihuangKubernetesXuexiBiji/img/loader.gif
HuweihuangKubernetesXuexiBiji/img/menu-icon.png
HuweihuangKubernetesXuexiBiji/img/save.png
HuweihuangKubernetesXuexiBiji/img/saved.png
HuweihuangKubernetesXuexiBiji/img/settings-s.png
HuweihuangKubernetesXuexiBiji/img/settings.png
HuweihuangKubernetesXuexiBiji/img/star.png
HuweihuangKubernetesXuexiBiji/js/__init__.py
HuweihuangKubernetesXuexiBiji/js/epub.js
HuweihuangKubernetesXuexiBiji/js/epub.min.js
HuweihuangKubernetesXuexiBiji/js/epub.min.map
HuweihuangKubernetesXuexiBiji/js/hooks.min.js
HuweihuangKubernetesXuexiBiji/js/hooks.min.map
HuweihuangKubernetesXuexiBiji/js/reader.js
HuweihuangKubernetesXuexiBiji/js/reader.js.map
HuweihuangKubernetesXuexiBiji/js/reader.min.js
HuweihuangKubernetesXuexiBiji/js/reader.min.map
HuweihuangKubernetesXuexiBiji/js/hooks/__init__.py
HuweihuangKubernetesXuexiBiji/js/hooks/extensions/__init__.py
HuweihuangKubernetesXuexiBiji/js/hooks/extensions/highlight.js
huweihuang_kubernetes_xuexi_biji-2024.3.6.0.dist-info/METADATA
huweihuang_kubernetes_xuexi_biji-2024.3.6.0.dist-info/WHEEL
huweihuang_kubernetes_xuexi_biji-2024.3.6.0.dist-info/entry_points.txt
huweihuang_kubernetes_xuexi_biji-2024.3.6.0.dist-info/top_level.txt
huweihuang_kubernetes_xuexi_biji-2024.3.6.0.dist-info/RECORD
